README.md
setup.cfg
setup.py
django_prepared_query/__init__.py
django_prepared_query/compiler.py
django_prepared_query/exceptions.py
django_prepared_query/manager.py
django_prepared_query/operations.py
django_prepared_query/params.py
django_prepared_query/query.py
django_prepared_query/queryset.py
django_prepared_query/statements_pool.py
django_prepared_query/utils.py
django_prepared_query/version.py
django_prepared_query.egg-info/PKG-INFO
django_prepared_query.egg-info/SOURCES.txt
django_prepared_query.egg-info/dependency_links.txt
django_prepared_query.egg-info/top_level.txt