Metadata-Version: 1.1
Name: django-prepared-query
Version: 0.3.1
Summary: Prepared statements support for Django
Home-page: https://github.com/DimaKudosh/django-prepared-query
Author: Dima Kudosh
Author-email: dimakudosh@gmail.com
License: MIT
Keywords: django,orm
Platform: UNKNOWN
Classifier: Development Status :: 4 - Beta
Classifier: Intended Audience :: Developers
Classifier: Operating System :: POSIX
Classifier: Programming Language :: Python
